needly/__init__.py
needly/needly.py
needly-2.5.95.dist-info/LICENSE
needly-2.5.95.dist-info/METADATA
needly-2.5.95.dist-info/WHEEL
needly-2.5.95.dist-info/entry_points.txt
needly-2.5.95.dist-info/RECORD
