Metadata-Version: 2.3
Name: needly
Version: 2.5.95
Summary: Python Needle Editor for openQA
License: GPLv3
Author: Lukáš Růžička
Author-email: lruzicka@redhat.com
Requires-Python: >=3.9
Classifier: License :: Other/Proprietary License
Classifier: Programming Language :: Python :: 3
Classifier: Programming Language :: Python :: 3.9
Classifier: Programming Language :: Python :: 3.10
Classifier: Programming Language :: Python :: 3.11
Classifier: Programming Language :: Python :: 3.12
Classifier: Programming Language :: Python :: 3.13
Requires-Dist: Pillow (>=11.0.0)
Requires-Dist: libvirt-python (>=11.0)
